jaxgl/__init__.py
jaxgl/maths.py
jaxgl/renderer.py
jaxgl/shaders.py
jaxgl-1.0.1.dist-info/LICENSE
jaxgl-1.0.1.dist-info/METADATA
jaxgl-1.0.1.dist-info/WHEEL
jaxgl-1.0.1.dist-info/top_level.txt
jaxgl-1.0.1.dist-info/RECORD
