Metadata-Version: 2.1
Name: jaxgl
Version: 1.0.1
Summary: An simple JAX graphics library
Author-email: Michael Matthews <michael.matthews@eng.ox.ac.uk>, Michael Beukman <michael.beukman@eng.ox.ac.uk>
Project-URL: Homepage, https://github.com/FLAIROx/JaxGL
Project-URL: Issues, https://github.com/FLAIROx/JaxGL
Classifier: Programming Language :: Python :: 3
Classifier: License :: OSI Approved :: MIT License
Classifier: Operating System :: OS Independent
Requires-Python: >=3.10
License-File: LICENSE
Requires-Dist: jax
Requires-Dist: flax
Requires-Dist: numpy
Requires-Dist: matplotlib
Requires-Dist: imageio
Provides-Extra: dev
Requires-Dist: black ; extra == 'dev'
Requires-Dist: pre-commit ; extra == 'dev'
